sphinx_mochi_theme/.gitignore
sphinx_mochi_theme/__init__.py
sphinx_mochi_theme/base.html
sphinx_mochi_theme/genindex.html
sphinx_mochi_theme/page.html
sphinx_mochi_theme/search.html
sphinx_mochi_theme/theme.conf
sphinx_mochi_theme/partials/brand.html
sphinx_mochi_theme/partials/footer.html
sphinx_mochi_theme/partials/icons.html
sphinx_mochi_theme/partials/mobile-header.html
sphinx_mochi_theme/partials/related-pages.html
sphinx_mochi_theme/partials/search.html
sphinx_mochi_theme/static/.gitignore
sphinx_mochi_theme/static/styles/theme.css
sphinx_mochi_theme-2023.7.8.dist-info/entry_points.txt
sphinx_mochi_theme-2023.7.8.dist-info/LICENSE
sphinx_mochi_theme-2023.7.8.dist-info/WHEEL
sphinx_mochi_theme-2023.7.8.dist-info/METADATA
sphinx_mochi_theme-2023.7.8.dist-info/RECORD
