Metadata-Version: 2.1
Name: sphinx_mochi_theme
Version: 2023.7.8
Summary: mochi, a plain sphinx theme for steady documentation platform 
Author: yamavol
Requires-Python: >=3.8
Classifier: Development Status :: 4 - Beta
Classifier: Framework :: Sphinx :: Theme
Classifier: Programming Language :: Python
Classifier: Programming Language :: Python :: 3
Classifier: License :: OSI Approved :: MIT License
Classifier: Topic :: Documentation
Classifier: Topic :: Software Development :: Documentation
Requires-Dist: sphinx >= 4.2
Requires-Dist: beautifulsoup4
Project-URL: Home, https://cobapen.github.io/sphinx-mochi-theme
Project-URL: Source, https://github.com/cobapen/sphinx-mochi-theme
